django_upgrade_check-1.1.0.dist-info/licenses/LICENSE
upgrade_check/__init__.py
upgrade_check/admin.py
upgrade_check/apps.py
upgrade_check/checks.py
upgrade_check/constraints.py
upgrade_check/models.py
upgrade_check/py.typed
upgrade_check/recorder.py
upgrade_check/signals.py
upgrade_check/upgrade_checks.py
upgrade_check/migrations/0001_initial.py
upgrade_check/migrations/__init__.py
django_upgrade_check-1.1.0.dist-info/METADATA
django_upgrade_check-1.1.0.dist-info/WHEEL
django_upgrade_check-1.1.0.dist-info/top_level.txt
django_upgrade_check-1.1.0.dist-info/RECORD
