Metadata-Version: 2.4
Name: django-upgrade-check
Version: 1.1.0
Summary: Integrate project upgrade checks in Django's system check framework
Author-email: Maykin Media <support@maykinmedia.nl>
License: Copyright 2025 Maykin Media
Project-URL: Homepage, https://github.com/maykinmedia/django-upgrade-check
Project-URL: Documentation, http://django-upgrade-check.readthedocs.io/en/latest/
Project-URL: Bug Tracker, https://github.com/maykinmedia/django-upgrade-check/issues
Project-URL: Source Code, https://github.com/maykinmedia/django-upgrade-check
Project-URL: Changelog, https://github.com/maykinmedia/django-upgrade-check/blob/main/CHANGELOG.rst
Keywords: Django,deploy,system checks
Classifier: Development Status :: 5 - Production/Stable
Classifier: Framework :: Django
Classifier: Framework :: Django :: 4.2
Classifier: Framework :: Django :: 5.2
Classifier: Intended Audience :: Developers
Classifier: Operating System :: Unix
Classifier: Operating System :: MacOS
Classifier: Operating System :: Microsoft :: Windows
Classifier: Programming Language :: Python :: 3.12
Classifier: Programming Language :: Python :: 3.13
Classifier: Topic :: Software Development :: Libraries :: Python Modules
Requires-Python: >=3.12
License-File: LICENSE
Requires-Dist: django>=4.2
Requires-Dist: semantic-version
Provides-Extra: tests
Requires-Dist: pytest; extra == "tests"
Requires-Dist: pytest-django; extra == "tests"
Requires-Dist: pytest-cov; extra == "tests"
Requires-Dist: tox; extra == "tests"
Requires-Dist: ruff; extra == "tests"
Requires-Dist: pyright; extra == "tests"
Requires-Dist: django-stubs; extra == "tests"
Provides-Extra: docs
Requires-Dist: sphinx; extra == "docs"
Requires-Dist: sphinx-rtd-theme; extra == "docs"
Provides-Extra: release
Requires-Dist: bump-my-version; extra == "release"
Dynamic: license-file
